jsoncls/__init__.py
jsoncls/jsoncls.py
jsoncls-1.0.2.dist-info/LICENSE
jsoncls-1.0.2.dist-info/METADATA
jsoncls-1.0.2.dist-info/WHEEL
jsoncls-1.0.2.dist-info/top_level.txt
jsoncls-1.0.2.dist-info/RECORD
