Metadata-Version: 2.1
Name: jsoncls
Version: 1.0.2
Summary: a library that supports both of python2 and python3, can load a json as an object, and also can dump an object to a json
Home-page: https://github.com/NieXiaoyi/jsoncls
Author: NieXiaoyi
Author-email: 756102681@qq.com
License: MIT
Classifier: Development Status :: 4 - Beta
Classifier: Programming Language :: Python :: 2
Classifier: Programming Language :: Python :: 3
Classifier: Intended Audience :: Developers
Classifier: License :: OSI Approved :: MIT License
Classifier: Topic :: Software Development :: Libraries
Classifier: Topic :: Utilities
Requires-Python: >=2.7, !=3.0.*, !=3.1.*, !=3.2.*, !=3.3.*, !=3.4.*, !=3.5.*
License-File: LICENSE
Requires-Dist: six >=1.12.0
